mcp_memory_service/__init__.py
mcp_memory_service/config.py
mcp_memory_service/dependency_check.py
mcp_memory_service/lm_studio_compat.py
mcp_memory_service/mcp_server.py
mcp_memory_service/server.py
mcp_memory_service/cli/__init__.py
mcp_memory_service/cli/ingestion.py
mcp_memory_service/cli/main.py
mcp_memory_service/cli/utils.py
mcp_memory_service/consolidation/__init__.py
mcp_memory_service/consolidation/associations.py
mcp_memory_service/consolidation/base.py
mcp_memory_service/consolidation/clustering.py
mcp_memory_service/consolidation/compression.py
mcp_memory_service/consolidation/consolidator.py
mcp_memory_service/consolidation/decay.py
mcp_memory_service/consolidation/forgetting.py
mcp_memory_service/consolidation/health.py
mcp_memory_service/consolidation/scheduler.py
mcp_memory_service/discovery/__init__.py
mcp_memory_service/discovery/client.py
mcp_memory_service/discovery/mdns_service.py
mcp_memory_service/embeddings/__init__.py
mcp_memory_service/embeddings/onnx_embeddings.py
mcp_memory_service/ingestion/__init__.py
mcp_memory_service/ingestion/base.py
mcp_memory_service/ingestion/chunker.py
mcp_memory_service/ingestion/pdf_loader.py
mcp_memory_service/ingestion/registry.py
mcp_memory_service/ingestion/text_loader.py
mcp_memory_service/models/__init__.py
mcp_memory_service/models/memory.py
mcp_memory_service/storage/__init__.py
mcp_memory_service/storage/base.py
mcp_memory_service/storage/chroma.py
mcp_memory_service/storage/chroma_enhanced.py
mcp_memory_service/storage/cloudflare.py
mcp_memory_service/storage/http_client.py
mcp_memory_service/storage/sqlite_vec.py
mcp_memory_service/sync/__init__.py
mcp_memory_service/sync/exporter.py
mcp_memory_service/sync/importer.py
mcp_memory_service/sync/litestream_config.py
mcp_memory_service/utils/__init__.py
mcp_memory_service/utils/db_utils.py
mcp_memory_service/utils/debug.py
mcp_memory_service/utils/hashing.py
mcp_memory_service/utils/http_server_manager.py
mcp_memory_service/utils/port_detection.py
mseep_mcp_memory_service-6.13.4.dist-info/METADATA
mseep_mcp_memory_service-6.13.4.dist-info/WHEEL
mseep_mcp_memory_service-6.13.4.dist-info/entry_points.txt
mseep_mcp_memory_service-6.13.4.dist-info/licenses/LICENSE
mseep_mcp_memory_service-6.13.4.dist-info/licenses/NOTICE
mseep_mcp_memory_service-6.13.4.dist-info/RECORD
